wehandle_aws_utils/__init__.py
wehandle_aws_utils/py.typed
wehandle_aws_utils/s3/utils.py
wehandle_aws_utils/secrets_manager/utils.py
wehandle_aws_utils-0.1.0.dist-info/WHEEL
wehandle_aws_utils-0.1.0.dist-info/METADATA
wehandle_aws_utils-0.1.0.dist-info/RECORD
