Metadata-Version: 2.3
Name: wehandle-aws-utils
Version: 0.1.0
Summary: Biblioteca para utilitários relacionados a AWS do time de automação
Author: Leonardo Pinheiro
Author-email: Leonardo Pinheiro <leonardo.pinheiro@wehandle.com>
Requires-Dist: boto3
Requires-Dist: botocore
Requires-Python: >=3.11
